dm_memorytasks/__init__.py
dm_memorytasks/_load_environment.py
dm_memorytasks/_version.py
dm_memorytasks/load_from_disk_test.py
dm_memorytasks/load_from_docker_test.py
dm_memorytasks-1.0.3.dist-info/LICENSE
dm_memorytasks-1.0.3.dist-info/METADATA
dm_memorytasks-1.0.3.dist-info/WHEEL
dm_memorytasks-1.0.3.dist-info/top_level.txt
dm_memorytasks-1.0.3.dist-info/RECORD
