Metadata-Version: 2.1
Name: dm-memorytasks
Version: 1.0.3
Summary: DeepMind Memory Tasks, a set of Unity-based machine-learning research tasks.
Home-page: UNKNOWN
Author: DeepMind
License: Apache License, Version 2.0
Keywords: reinforcement-learning python machine learning
Platform: UNKNOWN
Classifier: Development Status :: 5 - Production/Stable
Classifier: Environment :: Console
Classifier: Intended Audience :: Science/Research
Classifier: License :: OSI Approved :: Apache Software License
Classifier: Operating System :: POSIX :: Linux
Classifier: Operating System :: Microsoft :: Windows
Classifier: Operating System :: MacOS :: MacOS X
Classifier: Programming Language :: Python :: 3.7
Classifier: Topic :: Scientific/Engineering :: Artificial Intelligence
Requires-Python: >=3.7
Requires-Dist: absl-py
Requires-Dist: dm-env
Requires-Dist: dm-env-rpc (<1.1.0)
Requires-Dist: docker
Requires-Dist: grpcio
Requires-Dist: numpy
Requires-Dist: portpicker
Provides-Extra: examples
Requires-Dist: pygame ; extra == 'examples'
